odoo/addons/sale_order_invoicing_picking_filter/README.rst
odoo/addons/sale_order_invoicing_picking_filter/__init__.py
odoo/addons/sale_order_invoicing_picking_filter/__manifest__.py
odoo/addons/sale_order_invoicing_picking_filter/i18n/es.po
odoo/addons/sale_order_invoicing_picking_filter/i18n/it.po
odoo/addons/sale_order_invoicing_picking_filter/i18n/sale_order_invoicing_picking_filter.pot
odoo/addons/sale_order_invoicing_picking_filter/models/__init__.py
odoo/addons/sale_order_invoicing_picking_filter/models/sale_order.py
odoo/addons/sale_order_invoicing_picking_filter/models/sale_order_line.py
odoo/addons/sale_order_invoicing_picking_filter/models/stock_picking.py
odoo/addons/sale_order_invoicing_picking_filter/readme/CONTRIBUTORS.rst
odoo/addons/sale_order_invoicing_picking_filter/readme/DESCRIPTION.rst
odoo/addons/sale_order_invoicing_picking_filter/readme/USAGE.rst
odoo/addons/sale_order_invoicing_picking_filter/static/description/icon.png
odoo/addons/sale_order_invoicing_picking_filter/static/description/index.html
odoo/addons/sale_order_invoicing_picking_filter/tests/__init__.py
odoo/addons/sale_order_invoicing_picking_filter/tests/test_sale_order_invoicing_picking_filter.py
odoo/addons/sale_order_invoicing_picking_filter/views/stock_picking_views.xml
odoo/addons/sale_order_invoicing_picking_filter/wizard/__init__.py
odoo/addons/sale_order_invoicing_picking_filter/wizard/sale_advance_payment_inv.py
odoo/addons/sale_order_invoicing_picking_filter/wizard/sale_make_invoice_advanced_views.xml
odoo_addon_sale_order_invoicing_picking_filter-16.0.1.1.0.dist-info/METADATA
odoo_addon_sale_order_invoicing_picking_filter-16.0.1.1.0.dist-info/WHEEL
odoo_addon_sale_order_invoicing_picking_filter-16.0.1.1.0.dist-info/top_level.txt
odoo_addon_sale_order_invoicing_picking_filter-16.0.1.1.0.dist-info/RECORD
